kognitos/bdk/klang/__init__.py
kognitos/bdk/klang/lexer.py
kognitos/bdk/klang/parser.py
kognitos/bdk/klang/parser_signature.py
kognitos/bdk/klang/py.typed
kognitos/bdk/klang/token_type.py
kognitos_bdk_klang-2.2.2.dist-info/LICENSE
kognitos_bdk_klang-2.2.2.dist-info/METADATA
kognitos_bdk_klang-2.2.2.dist-info/WHEEL
kognitos_bdk_klang-2.2.2.dist-info/entry_points.txt
kognitos_bdk_klang-2.2.2.dist-info/RECORD
