Metadata-Version: 2.1
Name: kognitos-bdk-klang
Version: 2.2.2
Summary: A Signature parser for Kognitos book development kit (BDK)
License: Propietary
Author: Ignacio Delmont
Author-email: ignacio@kognitos.com
Requires-Python: >=3.9,<4.0
Classifier: License :: Other/Proprietary License
Classifier: Programming Language :: Python :: 3
Classifier: Programming Language :: Python :: 3.9
Classifier: Programming Language :: Python :: 3.10
Classifier: Programming Language :: Python :: 3.11
Classifier: Programming Language :: Python :: 3.12
Classifier: Programming Language :: Python :: 3.13
